lieer/__init__.py
lieer/gmailieer.py
lieer/local.py
lieer/nobar.py
lieer/remote.py
lieer-1.0.data/scripts/gmi
lieer-1.0.dist-info/COPYING.GPL-3.0+
lieer-1.0.dist-info/LICENSE.md
lieer-1.0.dist-info/METADATA
lieer-1.0.dist-info/WHEEL
lieer-1.0.dist-info/top_level.txt
lieer-1.0.dist-info/RECORD
