Metadata-Version: 2.1
Name: lieer
Version: 1.0
Summary: Fast fetch and two-way tag synchronization between notmuch and GMail
Home-page: https://github.com/gauteh/lieer
Author: Gaute Hope
Author-email: eg@gaute.vetsj.com
License: GPLv3+
Keywords: gmail notmuch synchronization tags
Platform: UNKNOWN
Classifier: Development Status :: 4 - Beta
Classifier: Programming Language :: Python :: 3
Requires-Dist: oauth2client (==4.1.3)
Requires-Dist: google-api-python-client (==1.7.11)
Requires-Dist: tqdm (==4.42.0)
Requires-Dist: notmuch
